finanzonline_uid/__init__.py
finanzonline_uid/__init__conf__.py
finanzonline_uid/__main__.py
finanzonline_uid/_datetime_utils.py
finanzonline_uid/behaviors.py
finanzonline_uid/cli.py
finanzonline_uid/config.py
finanzonline_uid/config_deploy.py
finanzonline_uid/config_show.py
finanzonline_uid/defaultconfig.toml
finanzonline_uid/enums.py
finanzonline_uid/i18n.py
finanzonline_uid/logging_setup.py
finanzonline_uid/mail.py
finanzonline_uid/py.typed
finanzonline_uid/adapters/__init__.py
finanzonline_uid/adapters/cache/__init__.py
finanzonline_uid/adapters/cache/file_cache.py
finanzonline_uid/adapters/finanzonline/__init__.py
finanzonline_uid/adapters/finanzonline/session_client.py
finanzonline_uid/adapters/finanzonline/uid_query_client.py
finanzonline_uid/adapters/formatting/__init__.py
finanzonline_uid/adapters/formatting/html_templates.py
finanzonline_uid/adapters/formatting/result_html.py
finanzonline_uid/adapters/notification/__init__.py
finanzonline_uid/adapters/notification/email_adapter.py
finanzonline_uid/adapters/notification/error_html_formatter.py
finanzonline_uid/adapters/notification/plain_formatter.py
finanzonline_uid/adapters/notification/rate_limit_formatter.py
finanzonline_uid/adapters/output/__init__.py
finanzonline_uid/adapters/output/formatters.py
finanzonline_uid/adapters/ratelimit/__init__.py
finanzonline_uid/adapters/ratelimit/rate_limit_tracker.py
finanzonline_uid/application/__init__.py
finanzonline_uid/application/ports.py
finanzonline_uid/application/use_cases.py
finanzonline_uid/defaultconfig.d/20-email.toml
finanzonline_uid/defaultconfig.d/30-logging.toml
finanzonline_uid/domain/__init__.py
finanzonline_uid/domain/errors.py
finanzonline_uid/domain/models.py
finanzonline_uid/domain/return_codes.py
finanzonline_uid/domain/soap_utils.py
finanzonline_uid/locales/messages.pot
finanzonline_uid/locales/de/LC_MESSAGES/messages.mo
finanzonline_uid/locales/de/LC_MESSAGES/messages.po
finanzonline_uid/locales/es/LC_MESSAGES/messages.mo
finanzonline_uid-2.5.6.dist-info/METADATA
finanzonline_uid-2.5.6.dist-info/WHEEL
finanzonline_uid-2.5.6.dist-info/entry_points.txt
finanzonline_uid-2.5.6.dist-info/licenses/LICENSE
finanzonline_uid-2.5.6.dist-info/RECORD
